pydevplus/__init__.py
pydevplus-0.1.1.dist-info/LICENSE
pydevplus-0.1.1.dist-info/METADATA
pydevplus-0.1.1.dist-info/WHEEL
pydevplus-0.1.1.dist-info/top_level.txt
pydevplus-0.1.1.dist-info/RECORD
