Metadata-Version: 2.2
Name: pydevplus
Version: 0.1.1
Summary: A versatile toolkit offering essential utilities to boost Python development productivity.
Home-page: https://github.com/sk-sanju/pydevplus
Author: sksanju
Author-email: sanjayskpy1@gmail.com
Classifier: Programming Language :: Python :: 3
Classifier: License :: OSI Approved :: MIT License
Classifier: Operating System :: OS Independent
Requires-Python: >=3.6
License-File: LICENSE
Dynamic: author
Dynamic: author-email
Dynamic: classifier
Dynamic: description
Dynamic: description-content-type
Dynamic: home-page
Dynamic: requires-python
Dynamic: summary
